datasette_gfm/__init__.py
datasette_gfm-0.1.1.dist-info/METADATA
datasette_gfm-0.1.1.dist-info/WHEEL
datasette_gfm-0.1.1.dist-info/entry_points.txt
datasette_gfm-0.1.1.dist-info/top_level.txt
datasette_gfm-0.1.1.dist-info/RECORD
