Metadata-Version: 2.1
Name: datasette-gfm
Version: 0.1.1
Summary: Export Datasette records as GitHub flavoured markdown
Home-page: https://github.com/postman-open-technologies/datasette-gfm
Author: Mike Ralphson
License: Apache License, Version 2.0
Project-URL: Issues, https://github.com/postman-open-technologies/datasette-gfm/issues
Project-URL: CI, https://github.com/postman-open-technologies/datasette-gfm/actions
Project-URL: Changelog, https://github.com/postman-open-technologies/datasette-gfm/releases
Platform: UNKNOWN
Requires-Dist: datasette
Provides-Extra: test
Requires-Dist: pytest ; extra == 'test'
Requires-Dist: pytest-asyncio ; extra == 'test'
Requires-Dist: httpx ; extra == 'test'
Requires-Dist: sqlite-utils ; extra == 'test'
